understory_cloud/__init__.py
understory_cloud/static/Inter-Black.woff
understory_cloud/static/Inter-Black.woff2
understory_cloud/static/Inter-BlackItalic.woff
understory_cloud/static/Inter-BlackItalic.woff2
understory_cloud/static/Inter-Bold.woff
understory_cloud/static/Inter-Bold.woff2
understory_cloud/static/Inter-BoldItalic.woff
understory_cloud/static/Inter-BoldItalic.woff2
understory_cloud/static/Inter-ExtraBold.woff
understory_cloud/static/Inter-ExtraBold.woff2
understory_cloud/static/Inter-ExtraBoldItalic.woff
understory_cloud/static/Inter-ExtraBoldItalic.woff2
understory_cloud/static/Inter-ExtraLight.woff
understory_cloud/static/Inter-ExtraLight.woff2
understory_cloud/static/Inter-ExtraLightItalic.woff
understory_cloud/static/Inter-ExtraLightItalic.woff2
understory_cloud/static/Inter-Italic.woff
understory_cloud/static/Inter-Italic.woff2
understory_cloud/static/Inter-Light.woff
understory_cloud/static/Inter-Light.woff2
understory_cloud/static/Inter-LightItalic.woff
understory_cloud/static/Inter-LightItalic.woff2
understory_cloud/static/Inter-Medium.woff
understory_cloud/static/Inter-Medium.woff2
understory_cloud/static/Inter-MediumItalic.woff
understory_cloud/static/Inter-MediumItalic.woff2
understory_cloud/static/Inter-Regular.woff
understory_cloud/static/Inter-Regular.woff2
understory_cloud/static/Inter-SemiBold.woff
understory_cloud/static/Inter-SemiBold.woff2
understory_cloud/static/Inter-SemiBoldItalic.woff
understory_cloud/static/Inter-SemiBoldItalic.woff2
understory_cloud/static/Inter-Thin.woff
understory_cloud/static/Inter-Thin.woff2
understory_cloud/static/Inter-ThinItalic.woff
understory_cloud/static/Inter-ThinItalic.woff2
understory_cloud/static/Inter-italic.var.woff2
understory_cloud/static/Inter-roman.var.woff2
understory_cloud/static/Inter.var.woff2
understory_cloud/static/gaea.gif
understory_cloud/static/iwc.svg
understory_cloud/static/moon.svg
understory_cloud/static/rainforest-stream.mp3
understory_cloud/static/sun.svg
understory.cloud-0.0.4.dist-info/entry_points.txt
understory.cloud-0.0.4.dist-info/LICENSE
understory.cloud-0.0.4.dist-info/WHEEL
understory.cloud-0.0.4.dist-info/METADATA
understory.cloud-0.0.4.dist-info/RECORD
