Metadata-Version: 2.1
Name: understory.cloud
Version: 0.0.4
Summary: Navigate the various projects tangential to the understory.
Home-page: https://understory.cloud/understory.cloud.git
License: CC0-1.0
Author: Angelo Gladding
Author-email: angelo@lahacker.net
Requires-Python: >=3.9,<3.10
Classifier: License :: CC0 1.0 Universal (CC0 1.0) Public Domain Dedication
Classifier: Programming Language :: Python :: 3
Classifier: Programming Language :: Python :: 3.9
Requires-Dist: understory
Project-URL: Repository, https://understory.cloud/understory.cloud.git
